MANIFEST.in
README.rst
setup.cfg
setup.py
urbanpyctionary/__init__.py
urbanpyctionary/cli.py
urbanpyctionary/client.py
urbanpyctionary/errors.py
urbanpyctionary.egg-info/PKG-INFO
urbanpyctionary.egg-info/SOURCES.txt
urbanpyctionary.egg-info/dependency_links.txt
urbanpyctionary.egg-info/entry_points.txt
urbanpyctionary.egg-info/pbr.json
urbanpyctionary.egg-info/requires.txt
urbanpyctionary.egg-info/top_level.txt