Metadata-Version: 1.1
Name: urbanpyctionary
Version: 0.86
Summary: An API wrapper to access Urban Dictionary.
Home-page: https://github.com/chrisvoncsefalvay/urbanpyctionary
Author: Chris von Csefalvay
Author-email: chris@chrisvoncsefalvay.com
License: MIT
Keywords: urbandictionary api wrapper
Platform: UNKNOWN
Classifier: Development Status :: 4 - Beta
Classifier: Topic :: Text Processing :: Linguistic
Classifier: License :: OSI Approved :: MIT License
Classifier: Programming Language :: Python :: 3
Classifier: Programming Language :: Python :: 3.2
Classifier: Programming Language :: Python :: 3.3
Classifier: Programming Language :: Python :: 3.4
